zcap-0.3.0.dist-info/METADATA
zcap-0.3.0.dist-info/WHEEL
zcap-0.3.0.dist-info/entry_points.txt
zcap-0.3.0.dist-info/licenses/LICENSE
zcap/.coverage
zcap/__init__.py
zcap/capability.py
zcap/contexts.py
zcap/models.py
zcap-0.3.0.dist-info/RECORD
