Metadata-Version: 2.1
Name: zcap
Version: 0.3.0
Summary: A pure Python implementation of ZCAP-LD (Authorization Capabilities for Linked Data)
Author-Email: Luke Hinds <luke@ir8.ai>
License: Apache License 2.0
Requires-Python: >=3.10
Requires-Dist: pyld>=2.0.0
Requires-Dist: cryptography>=45.0.0
Requires-Dist: pydantic>=2.0.0
Requires-Dist: rich>=14.0.0
Requires-Dist: base58>=2.1.1
Requires-Dist: pytest-asyncio>=1.0.0
Provides-Extra: test
Requires-Dist: pytest>=7.0.0; extra == "test"
Requires-Dist: pytest-cov>=4.0.0; extra == "test"
